femos/__init__.py
femos/core.py
femos/genotypes.py
femos/parser.py
femos/phenotypes.py
femos/selections.py
tests/__init__.py
tests/test_core.py
tests/test_genotypes.py
tests/test_phenotype.py
tests/test_selections.py
femos-0.0.19.dist-info/LICENSE
femos-0.0.19.dist-info/METADATA
femos-0.0.19.dist-info/WHEEL
femos-0.0.19.dist-info/top_level.txt
femos-0.0.19.dist-info/RECORD
